causaltensor/.vscode/settings.json
causaltensor/__init__.py
causaltensor/cauest/CovariancePCA.py
causaltensor/cauest/DID.py
causaltensor/cauest/DebiasConvex.py
causaltensor/cauest/DebiasConvexMissing.py
causaltensor/cauest/DebiasConvex_backup.py
causaltensor/cauest/MCNNM.py
causaltensor/cauest/OLSSyntheticControl.py
causaltensor/cauest/OLSSyntheticControl_old.py
causaltensor/cauest/Readme.ipynb
causaltensor/cauest/RobustSyntheticControl.py
causaltensor/cauest/Row_Specific_Treatments.py
causaltensor/cauest/SDID.py
causaltensor/cauest/__init__.py
causaltensor/cauest/panel_solver.py
causaltensor/cauest/result.py
causaltensor/matcomple/ALS_solver.py
causaltensor/matcomple/__init__.py
causaltensor/matcomple/hard_impute.py
causaltensor/matlib/__init__.py
causaltensor/matlib/generation.py
causaltensor/matlib/generation_treatment_pattern.py
causaltensor/matlib/util.py
causaltensor/sample_data/__init__.py
causaltensor/sample_data/fetch.ipynb
causaltensor/sample_data/fetch.py
causaltensor/tests/test_real_class.py
causaltensor/tests/test_synthetic_class.py
causaltensor-0.1.12.dist-info/LICENSE
causaltensor-0.1.12.dist-info/METADATA
causaltensor-0.1.12.dist-info/WHEEL
causaltensor-0.1.12.dist-info/RECORD
