Metadata-Version: 2.3
Name: causaltensor
Version: 0.1.12
Summary: Package for causal inference in panels
License: MIT
Keywords: causal,inference,panel,matrix,tensor
Author: Tianyi Peng
Author-email: tianyipeng95@gmail.com
Requires-Python: >=3.10,<4.0
Classifier: Intended Audience :: Science/Research
Classifier: License :: OSI Approved :: MIT License
Classifier: Programming Language :: Python
Classifier: Programming Language :: Python :: 3
Classifier: Programming Language :: Python :: 3.10
Classifier: Programming Language :: Python :: 3.11
Classifier: Programming Language :: Python :: 3.12
Classifier: Programming Language :: Python :: 3.13
Classifier: Topic :: Scientific/Engineering
Requires-Dist: cvxopt (>=1.2,<2.0)
Requires-Dist: cvxpy (>=1.4.3,<2.0.0)
Requires-Dist: importlib-metadata (>=3.0,<4.0) ; python_full_version <= "3.11.0"
Requires-Dist: matplotlib (>=3.8.0,<4.0.0)
Requires-Dist: numpy (>=1.18,<2.0)
Requires-Dist: pandas (>=2.1.0,<3.0.0)
Requires-Dist: toolz (>=0.12.1,<0.13.0)
Requires-Dist: tqdm (>=4.67.1,<5.0.0)
Project-URL: Homepage, https://github.com/TianyiPeng/causaltensor
Project-URL: Repository, https://github.com/TianyiPeng/causaltensor
